{"type":"PR","pr":{"number":18,"head":"f71ff7f239b17c3eda55e914c6e0d59847463416"},"user":"hand-dot","status":"draft","branch":"cms/コンポーネントの分割するデメリットと適切なタイミング","collection":"blog","title":"コンポーネントの分割するデメリットと適切なタイミング","description":"アトミックデザインなどでコンポーネントを分割したりするティップスがたくさんのブログや勉強会で紹介されていますが、それによるデメリットや適切なタイミングについて考えてみました。","objects":{"entry":{"path":"src/pages/blog/コンポーネントの分割するデメリットと適切なタイミング.md","sha":"0df1c6a2b76b2fb6d67c1e11abf3527c645e2e83"},"files":[{"path":"/static/img/undraw_done_checking_ty9a.png","sha":"7dbafa64d63b48d0481dcddf8cf28e95bda366e7"}]},"timeStamp":"2019-05-21T10:47:10.426Z"}